face_erase/__init__.py
face_erase/__main__.py
face_erase/blur.py
face_erase/child_stream.py
face_erase/detect.py
face_erase/ffmpeg.py
face_erase/ultralytics_util.py
face_erase/binary/yolov8n-face-640x640.torchscript
face_erase-0.1.0.dist-info/METADATA
face_erase-0.1.0.dist-info/WHEEL
face_erase-0.1.0.dist-info/top_level.txt
face_erase-0.1.0.dist-info/RECORD
