Metadata-Version: 2.1
Name: face-erase
Version: 0.1.0
Summary: UNKNOWN
Home-page: UNKNOWN
Author: Alex Nichol
License: UNKNOWN
Platform: UNKNOWN
Requires-Dist: Pillow
Requires-Dist: torch
Requires-Dist: torchvision
Requires-Dist: tqdm
